server.py
gridly_server_mcp-0.1.4.dist-info/METADATA
gridly_server_mcp-0.1.4.dist-info/WHEEL
gridly_server_mcp-0.1.4.dist-info/entry_points.txt
gridly_server_mcp-0.1.4.dist-info/top_level.txt
gridly_server_mcp-0.1.4.dist-info/RECORD
