Metadata-Version: 2.4
Name: gridly-server-mcp
Version: 0.1.4
Summary: Add your description here
Requires-Python: >=3.10
Requires-Dist: mcp[cli]>=1.9.0
